alu/alu_32bit.v
module alu_32bit(
    input  [31:0] op_1_in,
    input  [31:0] op_2_in,
    input  [3:0]  aluCtrl,
    output reg [31:0] result_out
);

always @(*) 
begin
    case (aluCtrl)

        4'b0000: result_out = op_1_in & op_2_in;                 // AND
        4'b0001: result_out = op_1_in | op_2_in;                 // OR
        4'b0010: result_out = op_1_in + op_2_in;                 // ADD
        4'b0011: result_out = op_1_in << op_2_in[4:0];           // SLL
        4'b0100: result_out = op_1_in ^ op_2_in;                 // XOR
        4'b0101: result_out = op_1_in >> op_2_in[4:0];           // SRL
        4'b0110: result_out = op_1_in - op_2_in;                 // SUB
        4'b0111: result_out = ($signed(op_1_in) < $signed(op_2_in)) ? 32'b1 : 32'b0; // SLT
        4'b1001: result_out = (op_1_in < op_2_in) ? 32'b1 : 32'b0; // SLTU
        4'b1101: result_out = $signed(op_1_in) >>> op_2_in[4:0]; // SRA
        4'b1000: result_out = op_2_in;                           // LUI

        default: result_out = 32'b0;

    endcase
end

endmodule

alu/alu_32bit_tb.v
`timescale 1ns/1ps

module alu_32bit_tb;

reg [31:0] op_1_in, op_2_in;
reg [3:0] aluCtrl;
wire [31:0] result_out;

alu_32bit dut (
    .op_1_in(op_1_in),
    .op_2_in(op_2_in),
    .aluCtrl(aluCtrl),
    .result_out(result_out)
);

initial 
begin

$dumpfile("alu_32bit.vcd");
$dumpvars(0, alu_32bit_tb);


// AND
op_1_in = 32'hF0F0F0F0;
op_2_in = 32'h0F0F0F0F;
aluCtrl= 4'b0000;
#10;
$display("AND: %h & %h = %h", op_1_in, op_2_in, result_out);

// OR
aluCtrl= 4'b0001;
#10;
$display("OR: %h | %h = %h", op_1_in, op_2_in, result_out);

// ADD
op_1_in = 5; 
op_2_in = 3; 
aluCtrl= 4'b0010;
#10;
$display("ADD: %d + %d = %d", op_1_in, op_2_in, result_out);

// SLL
op_1_in = 1;
op_2_in = 5;
aluCtrl= 4'b0011;
#10;
$display("SLL: %h << %d = %h", op_1_in, op_2_in, result_out);

// XOR
op_1_in = 32'hAAAA5555;
op_2_in = 32'hFFFF0000;
aluCtrl = 4'b0100;
#10;
$display("XOR: %h ^ %h = %h", op_1_in, op_2_in, result_out);

// SRL
op_1_in = 32'h80000000;
op_2_in = 1;
aluCtrl= 4'b0101;
#10;
$display("SRL: %h >> %d = %h", op_1_in, op_2_in, result_out);

// SUB
op_1_in = 5; 
op_2_in = 3; 
aluCtrl= 4'b0110;
#10;
$display("SUB: %d - %d = %d", op_1_in, op_2_in, result_out);


// SLT
op_1_in = 32'hFFFFFFFF;
op_2_in = 1;
aluCtrl= 4'b0111;
#10;
$display("SLT: %h < %h = %d", op_1_in, op_2_in, result_out);

// SLTU
aluCtrl= 4'b1001;
#10;
$display("SLTU: %h < %h = %d", op_1_in, op_2_in, result_out);

// SRA
aluCtrl= 4'b1101;
#10;
$display("SRA: %h >>> %d = %h", op_1_in, op_2_in, result_out);

// LUI
op_1_in = 0;
op_2_in = 32'h12345000;
aluCtrl = 4'b1000;
#10;
$display("LUI: result = %h", result_out);

$finish;

end

endmodule

alu_32bit.vcd
$date
	Fri Mar  6 10:08:22 2026
$end
$version
	Icarus Verilog
$end
$timescale
	1ps
$end
$scope module alu_32bit_tb $end
$var wire 32 ! result_out [31:0] $end
$var reg 4 " aluCtrl [3:0] $end
$var reg 32 # op_1_in [31:0] $end
$var reg 32 $ op_2_in [31:0] $end
$scope module dut $end
$var wire 4 % aluCtrl [3:0] $end
$var wire 32 & op_1_in [31:0] $end
$var wire 32 ' op_2_in [31:0] $end
$var reg 32 ( result_out [31:0] $end
$upscope $end
$upscope $end
$enddefinitions $end
$comment Show the parameter values. $end
$dumpall
$end
#0
$dumpvars
b0 (
b1111000011110000111100001111 '
b11110000111100001111000011110000 &
b0 %
b1111000011110000111100001111 $
b11110000111100001111000011110000 #
b0 "
b0 !
$end
#10000
b11111111111111111111111111111111 !
b11111111111111111111111111111111 (
b1 "
b1 %
#20000
b1000 !
b1000 (
b10 "
b10 %
b11 $
b11 '
b101 #
b101 &
#30000
b100000 !
b100000 (
b11 "
b11 %
b101 $
b101 '
b1 #
b1 &
#40000
b1010101010101010101010101010101 !
b1010101010101010101010101010101 (
b100 "
b100 %
b11111111111111110000000000000000 $
b11111111111111110000000000000000 '
b10101010101010100101010101010101 #
b10101010101010100101010101010101 &
#50000
b1000000000000000000000000000000 !
b1000000000000000000000000000000 (
b101 "
b101 %
b1 $
b1 '
b10000000000000000000000000000000 #
b10000000000000000000000000000000 &
#60000
b10 !
b10 (
b110 "
b110 %
b11 $
b11 '
b101 #
b101 &
#70000
b1 !
b1 (
b111 "
b111 %
b1 $
b1 '
b11111111111111111111111111111111 #
b11111111111111111111111111111111 &
#80000
b0 !
b0 (
b1001 "
b1001 %
#90000
b11111111111111111111111111111111 !
b11111111111111111111111111111111 (
b1101 "
b1101 %
#100000
b10010001101000101000000000000 !
b10010001101000101000000000000 (
b1000 "
b1000 %
b10010001101000101000000000000 $
b10010001101000101000000000000 '
b0 #
b0 &
