aluControl/aluControl.v
module aluControl(
    input [2:0] ALUop,       // From main Control Unit
    input [2:0] funct3,      // instruction[14:12]
    input funct7_5,          // instruction[30]
    output reg [3:0] aluCtrl // To ALU
);

    // funct3 parameters
    parameter FUNCT3_ADD  = 3'b000;
    parameter FUNCT3_SLL  = 3'b001;
    parameter FUNCT3_SLT  = 3'b010;
    parameter FUNCT3_SLTU = 3'b011;
    parameter FUNCT3_XOR  = 3'b100;
    parameter FUNCT3_SRL  = 3'b101;
    parameter FUNCT3_OR   = 3'b110;
    parameter FUNCT3_AND  = 3'b111;

    always @(*) begin
        case (ALUop)

            // Load / Store / JALR
            3'b000: aluCtrl = 4'b0010;   // ADD

            // Branch
            3'b001: aluCtrl = 4'b0110;   // SUB

            // R-type and I-type arithmetic
            3'b010: begin
                case (funct3)

                    FUNCT3_ADD: begin
                        if (funct7_5)
                            aluCtrl = 4'b0110; // SUB
                        else
                            aluCtrl = 4'b0010; // ADD
                    end

                    FUNCT3_AND: aluCtrl = 4'b0000; // AND

                    FUNCT3_OR:  aluCtrl = 4'b0001; // OR

                    FUNCT3_SLT: aluCtrl = 4'b0111; // SLT

                    FUNCT3_SLTU: aluCtrl = 4'b1001; // SLTU

                    FUNCT3_XOR: aluCtrl = 4'b0100; // XOR

                    FUNCT3_SLL: aluCtrl = 4'b0011; // SLL

                    FUNCT3_SRL: begin
                        if (funct7_5)
                            aluCtrl = 4'b1101; // SRA
                        else
                            aluCtrl = 4'b0101; // SRL
                    end

                    default: aluCtrl = 4'b1111;

                endcase
            end

            // LUI
            3'b100: aluCtrl = 4'b1000;

            default: aluCtrl = 4'b0010;

        endcase
    end

endmodule

aluControl/aluControl_tb.v
`timescale 1ns/1ps

module aluControl_tb;

reg [2:0] ALUop;
reg [2:0] funct3;
reg funct7_5;

wire [3:0] aluCtrl;

aluControl dut (
    .ALUop(ALUop),
    .funct3(funct3),
    .funct7_5(funct7_5),
    .aluCtrl(aluCtrl)
);

initial begin

$dumpfile("aluControl.vcd");
$dumpvars(0, aluControl_tb);

// Load / Store (ADD)
ALUop = 3'b000; funct3 = 3'b000; funct7_5 = 0;
#10;
$display("LOAD/STORE : aluCtrl = %b (ADD expected)", aluCtrl);

// Branch (SUB)
ALUop = 3'b001; funct3 = 3'b000; funct7_5 = 0;
#10;
$display("BRANCH : aluCtrl = %b (SUB expected)", aluCtrl);

// ADD
ALUop = 3'b010; funct3 = 3'b000; funct7_5 = 0;
#10;
$display("ADD : aluCtrl = %b", aluCtrl);

// SUB
ALUop = 3'b010; funct3 = 3'b000; funct7_5 = 1;
#10;
$display("SUB : aluCtrl = %b", aluCtrl);

// AND
ALUop = 3'b010; funct3 = 3'b111; funct7_5 = 0;
#10;
$display("AND : aluCtrl = %b", aluCtrl);

// OR
ALUop = 3'b010; funct3 = 3'b110; funct7_5 = 0;
#10;
$display("OR : aluCtrl = %b", aluCtrl);

// XOR
ALUop = 3'b010; funct3 = 3'b100; funct7_5 = 0;
#10;
$display("XOR : aluCtrl = %b", aluCtrl);

// SLL
ALUop = 3'b010; funct3 = 3'b001; funct7_5 = 0;
#10;
$display("SLL : aluCtrl = %b", aluCtrl);

// SRL
ALUop = 3'b010; funct3 = 3'b101; funct7_5 = 0;
#10;
$display("SRL : aluCtrl = %b", aluCtrl);

// SRA
ALUop = 3'b010; funct3 = 3'b101; funct7_5 = 1;
#10;
$display("SRA : aluCtrl = %b", aluCtrl);

// SLT
ALUop = 3'b010; funct3 = 3'b010; funct7_5 = 0;
#10;
$display("SLT : aluCtrl = %b", aluCtrl);

// SLTU
ALUop = 3'b010; funct3 = 3'b011; funct7_5 = 0;
#10;
$display("SLTU : aluCtrl = %b", aluCtrl);

// LUI
ALUop = 3'b100; funct3 = 3'b000; funct7_5 = 0;
#10;
$display("LUI : aluCtrl = %b", aluCtrl);

$finish;

end

endmodule

aluControl.vcd
$date
	Fri Mar  6 10:09:53 2026
$end
$version
	Icarus Verilog
$end
$timescale
	1ps
$end
$scope module aluControl_tb $end
$var wire 4 ! aluCtrl [3:0] $end
$var reg 3 " ALUop [2:0] $end
$var reg 3 # funct3 [2:0] $end
$var reg 1 $ funct7_5 $end
$scope module dut $end
$var wire 3 % ALUop [2:0] $end
$var wire 3 & funct3 [2:0] $end
$var wire 1 $ funct7_5 $end
$var parameter 3 ' FUNCT3_ADD $end
$var parameter 3 ( FUNCT3_AND $end
$var parameter 3 ) FUNCT3_OR $end
$var parameter 3 * FUNCT3_SLL $end
$var parameter 3 + FUNCT3_SLT $end
$var parameter 3 , FUNCT3_SLTU $end
$var parameter 3 - FUNCT3_SRL $end
$var parameter 3 . FUNCT3_XOR $end
$var reg 4 / aluCtrl [3:0] $end
$upscope $end
$upscope $end
$enddefinitions $end
$comment Show the parameter values. $end
$dumpall
b100 .
b101 -
b11 ,
b10 +
b1 *
b110 )
b111 (
b0 '
$end
#0
$dumpvars
b10 /
b0 &
b0 %
0$
b0 #
b0 "
b10 !
$end
#10000
b110 !
b110 /
b1 "
b1 %
#20000
b10 !
b10 /
b10 "
b10 %
#30000
b110 !
b110 /
1$
#40000
b0 !
b0 /
0$
b111 #
b111 &
#50000
b1 !
b1 /
b110 #
b110 &
#60000
b100 !
b100 /
b100 #
b100 &
#70000
b11 !
b11 /
b1 #
b1 &
#80000
b101 !
b101 /
b101 #
b101 &
#90000
b1101 !
b1101 /
1$
#100000
b111 !
b111 /
0$
b10 #
b10 &
#110000
b1001 !
b1001 /
b11 #
b11 &
#120000
b1000 !
b1000 /
b0 #
b0 &
b100 "
b100 %
