controlUnit/controlUnit.v
module controlUnit(
    input [6:0] opCode,
    output reg regWrite,
    output reg ALUsrc,
    output reg memRead,
    output reg memWrite,
    output reg memToReg,
    output reg branch,
    output reg jump,
    output reg [2:0] ALUop
);
always @ (*)
begin
    regWrite = 1'b0;
    ALUsrc = 1'b0;
    memRead = 1'b0;
    memWrite = 1'b0;
    memToReg = 1'b0;
    branch = 1'b0;
    jump = 1'b0;
    ALUop = 3'b000;
    case (opCode)
    7'b0110011 :                 // R type 
    begin
        regWrite = 1'b1;
        ALUop = 3'b010;
    end
    7'b0010011 :                 // I Type
    begin
        regWrite = 1'b1;
        ALUsrc = 1'b1;
        ALUop = 3'b010;
    end
    7'b0000011 :                 // Load type 
    begin
        regWrite = 1'b1;
        ALUsrc = 1'b1;
        memRead = 1'b1;
        memToReg = 1'b1;
    end
    7'b0100011 :                 // Store type 
    begin
        ALUsrc = 1'b1;
        memWrite = 1'b1;
        memToReg = 1'b0;         // memToReg = 1'bx
    end
    7'b1100011 :                 // Branch type
    begin
        memToReg = 1'b0;         // memToReg = 1'bx
        branch = 1'b1;
        ALUop = 3'b001;
    end
    7'b1101111 :                 // JAL Type
    begin
        regWrite = 1'b1;
        ALUsrc = 1'b0;           // ALUrsc = 1'bx
        jump = 1'b1;
        ALUop = 3'b000;          // ALUop = 3'bxxx
    end
    7'b1100111 :                 // JALR Type
    begin
        regWrite = 1'b1;
        ALUsrc = 1'b1;
        jump = 1'b1;
    end
    7'b0110111 :                 // LUI Type
    begin
        regWrite = 1'b1;
        ALUsrc = 1'b1;
        ALUop = 3'b100;
    end
    7'b0010111 :                 // AUIPC Type
    begin
        regWrite = 1'b1;
        ALUsrc = 1'b1;
    end
    7'b1110011 :                 // System Type
    begin
        ALUop = 3'b000;          // ALUop = 3'bxxx
    end
    default : ;
    endcase 
end
endmodule

controlUnit/controlUnit_tb.v
`timescale 1ns/1ps
module controlUnit_tb;
reg [6:0] opCode;
wire regWrite;
wire ALUsrc;
wire memRead;
wire memWrite;
wire memToReg;
wire branch;
wire jump;
wire [2:0] ALUop;
controlUnit dut (
    .opCode(opCode),
    .regWrite(regWrite),
    .ALUsrc(ALUsrc),
    .memRead(memRead),
    .memWrite(memWrite),
    .memToReg(memToReg),
    .branch(branch),
    .jump(jump),
    .ALUop(ALUop)
);

initial begin
$dumpfile("controlUnit.vcd");
$dumpvars(0,controlUnit_tb);
$display("Opcode   regWrite ALUsrc memRead memWrite memToReg branch jump ALUop");

// R type
opCode = 7'b0110011; #10;

// I type
opCode = 7'b0010011; #10;

// Load
opCode = 7'b0000011; #10;

// Store
opCode = 7'b0100011; #10;

// Branch
opCode = 7'b1100011; #10;

// JAL
opCode = 7'b1101111; #10;

// JALR
opCode = 7'b1100111; #10;

// LUI
opCode = 7'b0110111; #10;

// AUIPC
opCode = 7'b0010111; #10;

// System
opCode = 7'b1110011; #10;

$finish;

end

// monitor changes
initial begin
$monitor("%b   %b %b %b %b %b %b %b %b",
        opCode, regWrite, ALUsrc, memRead,
        memWrite, memToReg, branch, jump, ALUop);
end

endmodule

controlUnit.vcd
$date
	Thu Mar  5 09:57:59 2026
$end
$version
	Icarus Verilog
$end
$timescale
	1ps
$end
$scope module controlUnit_tb $end
$var wire 1 ! regWrite $end
$var wire 1 " memWrite $end
$var wire 1 # memToReg $end
$var wire 1 $ memRead $end
$var wire 1 % jump $end
$var wire 1 & branch $end
$var wire 1 ' ALUsrc $end
$var wire 3 ( ALUop [2:0] $end
$var reg 7 ) opCode [6:0] $end
$scope module dut $end
$var wire 7 * opCode [6:0] $end
$var reg 3 + ALUop [2:0] $end
$var reg 1 ' ALUsrc $end
$var reg 1 & branch $end
$var reg 1 % jump $end
$var reg 1 $ memRead $end
$var reg 1 # memToReg $end
$var reg 1 " memWrite $end
$var reg 1 ! regWrite $end
$upscope $end
$upscope $end
$enddefinitions $end
$comment Show the parameter values. $end
$dumpall
$end
#0
$dumpvars
b10 +
b110011 *
b110011 )
b10 (
0'
0&
0%
0$
0#
0"
1!
$end
#10000
1'
b10 (
b10 +
1!
b10011 )
b10011 *
#20000
1#
1$
b0 (
b0 +
1'
1!
b11 )
b11 *
#30000
1"
0#
0$
1'
0!
b100011 )
b100011 *
#40000
b1 (
b1 +
1&
0"
0'
b1100011 )
b1100011 *
#50000
1%
1!
b0 (
b0 +
0&
b1101111 )
b1101111 *
#60000
1'
1%
1!
b1100111 )
b1100111 *
#70000
b100 (
b100 +
0%
1'
1!
b110111 )
b110111 *
#80000
b0 (
b0 +
1'
1!
b10111 )
b10111 *
#90000
0'
0!
b1110011 )
b1110011 *
