dataMemory/dataMemory.v
module dataMemory(
    input clk,
    input rst,
    input memRead,
    input memWrite,
    input [31:0] Address,
    input [31:0] write_data,
    output [31:0] read_data
);

reg [31:0] Dmemory [0:31];

assign read_data = Dmemory[Address >> 2]; // Memory always outputs data; CPU control logic decides whether to use it
integer i;
always @ (posedge clk)
begin 
    if(rst)
    begin
        for(i = 0; i<32; i = i +1)
        begin
            Dmemory[i] <= 32'h0;
        end
    end
    else
    begin
        if(memWrite) Dmemory[Address >> 2] <= write_data;
    end
end
endmodule

dataMemory/dataMemory_tb.v
`timescale 1ns/1ps

module dataMemory_tb;

reg clk;
reg rst;
reg memRead;
reg memWrite;
reg [31:0] Address;
reg [31:0] write_data;
wire [31:0] read_data;

dataMemory dut(
    .clk(clk),
    .rst(rst),
    .memRead(memRead),
    .memWrite(memWrite),
    .Address(Address),
    .write_data(write_data),
    .read_data(read_data)
);

always #5 clk = ~clk;

initial
begin
$dumpfile("dataMemory.vcd");
$dumpvars(0,dataMemory_tb);

clk = 0;
rst = 1;
memRead = 0;
memWrite = 0;

#10;
rst = 0;
// WRITE TEST
Address = 32'd4;
write_data = 32'd100;
memWrite = 1;
#10;

memWrite = 0;

// READ TEST
memRead = 1;
Address = 32'd4;
#10;

$display("Read Data = %d", read_data); //32'd100


// SECOND WRITE
Address = 32'd8;
write_data = 32'd55;
memWrite = 1;
#10;

memWrite = 0;

// SECOND READ
Address = 32'd8;
#10;

$display("Read Data = %d", read_data); // 32'd55

#20;
$finish;

end

endmodule

dataMemory.vcd
$date
	Fri Mar  6 09:42:30 2026
$end
$version
	Icarus Verilog
$end
$timescale
	1ps
$end
$scope module dataMemory_tb $end
$var wire 32 ! read_data [31:0] $end
$var reg 32 " Address [31:0] $end
$var reg 1 # clk $end
$var reg 1 $ memRead $end
$var reg 1 % memWrite $end
$var reg 1 & rst $end
$var reg 32 ' write_data [31:0] $end
$scope module dut $end
$var wire 32 ( Address [31:0] $end
$var wire 1 # clk $end
$var wire 1 $ memRead $end
$var wire 1 % memWrite $end
$var wire 32 ) read_data [31:0] $end
$var wire 1 & rst $end
$var wire 32 * write_data [31:0] $end
$var integer 32 + i [31:0] $end
$upscope $end
$upscope $end
$enddefinitions $end
$comment Show the parameter values. $end
$dumpall
$end
#0
$dumpvars
bx +
bx *
bx )
bx (
bx '
1&
0%
0$
0#
bx "
bx !
$end
#5000
b100000 +
1#
#10000
b0 !
b0 )
0#
1%
b1100100 '
b1100100 *
b100 "
b100 (
0&
#15000
b1100100 !
b1100100 )
1#
#20000
0#
1$
0%
#25000
1#
#30000
b0 !
b0 )
0#
1%
b110111 '
b110111 *
b1000 "
b1000 (
#35000
b110111 !
b110111 )
1#
#40000
0#
0%
