PC.v
module PC(
    input [31:0] pc_in,
    input clk,
    input rst,
    output reg [31:0] pc_out
);
always @(posedge clk) 
begin
    if(rst)
        pc_out<=32'd0;
    else
        pc_out<=pc_in;
end
endmodule

PC/PC_tb.v
`timescale 1ns/1ps

module PC_tb;

reg [31:0] pc_in;
reg clk;
reg rst;
wire [31:0] pc_out;

PC dut(
    .pc_in(pc_in),
    .clk(clk),
    .rst(rst),
    .pc_out(pc_out)
);

always #5 clk = ~clk;

initial 
begin
    $dumpfile("PC.vcd");
    $dumpvars(0,PC_tb);
    $monitor("Time=%0t | rst=%b | pc_in=%d | pc_out=%d", 
              $time, rst, pc_in, pc_out);

    clk = 0;
    rst = 1;
    pc_in = 32'd0;

    // Apply reset
    #10 rst = 0;

    // Apply different PC inputs
    #10 pc_in = 32'd4;
    #10 pc_in = 32'd8;
    #10 pc_in = 32'd12;
    #10 pc_in = 32'd16;

    // Apply reset again
    #10 rst = 1;
    #10 rst = 0;

    #20 $finish;
end


endmodule

PC.vcd
$date
	Fri Mar  6 08:22:20 2026
$end
$version
	Icarus Verilog
$end
$timescale
	1ps
$end
$scope module PC_tb $end
$var wire 32 ! pc_out [31:0] $end
$var reg 1 " clk $end
$var reg 32 # pc_in [31:0] $end
$var reg 1 $ rst $end
$scope module dut $end
$var wire 1 " clk $end
$var wire 32 % pc_in [31:0] $end
$var wire 1 $ rst $end
$var reg 32 & pc_out [31:0] $end
$upscope $end
$upscope $end
$enddefinitions $end
$comment Show the parameter values. $end
$dumpall
$end
#0
$dumpvars
bx &
b0 %
1$
b0 #
0"
bx !
$end
#5000
b0 !
b0 &
1"
#10000
0"
0$
#15000
1"
#20000
0"
b100 #
b100 %
#25000
b100 !
b100 &
1"
#30000
0"
b1000 #
b1000 %
#35000
b1000 !
b1000 &
1"
#40000
0"
b1100 #
b1100 %
#45000
b1100 !
b1100 &
1"
#50000
0"
b10000 #
b10000 %
#55000
b10000 !
b10000 &
1"
#60000
0"
1$
#65000
b0 !
b0 &
1"
#70000
0"
0$
#75000
b10000 !
b10000 &
1"
