registerFile/registerFile.v
module registerFile(
    input clk,
    input rst,         // sync reset 
    input [4:0] rs1,   // 5 bit source register 1
    input [4:0] rs2,   // 5 bit source register 2
    input [4:0] rd,    // 5 bit destination register 
    input regWrite,    // Register write enable signal
    input [31:0] writeData, // Data to be written into destination register
    output [31:0] readData1,// Data read from source register 1
    output [31:0] readData2 // Data read from source register 2
);
// 32 registers with 32 bit width 
reg [31:0] registers[0:31];

// x0 should always read as 0 (RISC-V spec)
assign readData1 = (rs1 == 0) ? 32'b0 : registers[rs1];
assign readData2 = (rs2 == 0) ? 32'b0 : registers[rs2];

integer i;
always @ (posedge clk)
begin
    if(rst)
    begin
        for(i = 0; i < 32 ; i=i+1)
        begin
            registers[i] <= 32'h0;
        end
    end
    else if(regWrite && rd!=5'd0) // Only write if regWrite is high AND destination is not x0 
    begin
        registers[rd] <= writeData ;
    end
end
always @(posedge clk) begin
    if (regWrite)
        $display("WRITE: rd=%d data=%d", rd, writeData);
end
endmodule

registerFile/registerFile_tb.v
`timescale 1ns/1ps

module registerFile_tb;

    reg clk;
    reg rst;
    reg [4:0] rs1, rs2, rd;
    reg regWrite;
    reg [31:0] writeData;
    wire [31:0] readData1, readData2;

    // Instantiate the register file
    registerFile uut (
        .clk(clk),
        .rst(rst),
        .rs1(rs1),
        .rs2(rs2),
        .rd(rd),
        .regWrite(regWrite),
        .writeData(writeData),
        .readData1(readData1),
        .readData2(readData2)
    );

    // Clock generation: 10ns period
    initial clk = 0;
    always #5 clk = ~clk;

    initial begin
        $dumpfile("registerFile.vcd");
        $dumpvars(0, registerFile_tb);

        // Initialize
        rst = 1;
        regWrite = 0;
        rs1 = 0; rs2 = 0; rd = 0; writeData = 0;

        #10;         // wait one clock
        rst = 0;     // release reset

        // ------------------- Test 1: Write to x1 and read -------------------
        rd = 5'd1;
        writeData = 32'hA5A5A5A5;
        regWrite = 1;
        #10;         // wait one clock to write

        // Read back
        rs1 = 5'd1;
        rs2 = 5'd0;  // x0 should always read 0
        #1;          // small delay for combinational read
        $display("Read x1: %h, Read x0: %h", readData1, readData2);

        // ------------------- Test 2: Write to x2 and read -------------------
        rd = 5'd2;
        writeData = 32'h12345678;
        #10;         // wait one clock to write

        rs1 = 5'd1;  // read x1
        rs2 = 5'd2;  // read x2
        #1;
        $display("Read x1: %h, Read x2: %h", readData1, readData2);

        // ------------------- Test 3: Try writing to x0 (should be ignored) -------------------
        rd = 5'd0;
        writeData = 32'hFFFFFFFF;
        #10;
        rs1 = 5'd0;
        #1;
        $display("Read x0 after write attempt: %h", readData1);

        $finish;
    end

endmodule

registerFile.vcd
$date
	Fri Mar  6 08:50:06 2026
$end
$version
	Icarus Verilog
$end
$timescale
	1ps
$end
$scope module registerFile_tb $end
$var wire 32 ! readData2 [31:0] $end
$var wire 32 " readData1 [31:0] $end
$var reg 1 # clk $end
$var reg 5 $ rd [4:0] $end
$var reg 1 % regWrite $end
$var reg 5 & rs1 [4:0] $end
$var reg 5 ' rs2 [4:0] $end
$var reg 1 ( rst $end
$var reg 32 ) writeData [31:0] $end
$scope module uut $end
$var wire 1 # clk $end
$var wire 5 * rd [4:0] $end
$var wire 1 % regWrite $end
$var wire 5 + rs1 [4:0] $end
$var wire 5 , rs2 [4:0] $end
$var wire 1 ( rst $end
$var wire 32 - writeData [31:0] $end
$var wire 32 . readData2 [31:0] $end
$var wire 32 / readData1 [31:0] $end
$var integer 32 0 i [31:0] $end
$upscope $end
$upscope $end
$enddefinitions $end
$comment Show the parameter values. $end
$dumpall
$end
#0
$dumpvars
bx 0
b0 /
b0 .
b0 -
b0 ,
b0 +
b0 *
b0 )
1(
b0 '
b0 &
0%
b0 $
0#
b0 "
b0 !
$end
#5000
b100000 0
1#
#10000
0#
1%
b10100101101001011010010110100101 )
b10100101101001011010010110100101 -
b1 $
b1 *
0(
#15000
1#
#20000
b10100101101001011010010110100101 "
b10100101101001011010010110100101 /
0#
b1 &
b1 +
#21000
b10010001101000101011001111000 )
b10010001101000101011001111000 -
b10 $
b10 *
#25000
1#
#30000
0#
#31000
b10010001101000101011001111000 !
b10010001101000101011001111000 .
b10 '
b10 ,
#32000
b11111111111111111111111111111111 )
b11111111111111111111111111111111 -
b0 $
b0 *
#35000
1#
#40000
0#
#42000
b0 "
b0 /
b0 &
b0 +
