mux2to1/mux2to1.v
module mux2to1(a,b,y,sel);
input [31:0]a;
input [31:0]b;
input sel;
output reg [31:0]y;
always @(*)
begin
    case(sel)
    1'b0 :y = a;
    1'b1 :y = b;
    default:y=1'bx;
    endcase
end
endmodule

adder/adder.v
module adder(
    input [31:0] a,
    input [31:0] b,
    output [31:0] y
);
assign y = a + b;
endmodule

dataMemory/dataMemory.v
module dataMemory(
    input clk,
    input rst,
    input memRead,
    input memWrite,
    input [31:0] Address,
    input [31:0] write_data,
    output [31:0] read_data
);

reg [31:0] Dmemory [0:31];

assign read_data = Dmemory[Address >> 2]; // Memory always outputs data; CPU control logic decides whether to use it
integer i;
always @ (posedge clk)
begin 
    if(rst)
    begin
        for(i = 0; i<32; i = i +1)
        begin
            Dmemory[i] <= 32'h0;
        end
    end
    else
    begin
        if(memWrite) Dmemory[Address >> 2] <= write_data;
    end
end
endmodule

controlUnit/controlUnit.v
module controlUnit(
    input [6:0] opCode,
    output reg regWrite,
    output reg ALUsrc,
    output reg memRead,
    output reg memWrite,
    output reg memToReg,
    output reg branch,
    output reg jump,
    output reg [2:0] ALUop
);
always @ (*)
begin
    regWrite = 1'b0;
    ALUsrc = 1'b0;
    memRead = 1'b0;
    memWrite = 1'b0;
    memToReg = 1'b0;
    branch = 1'b0;
    jump = 1'b0;
    ALUop = 3'b000;
    case (opCode)
    7'b0110011 :                 // R type 
    begin
        regWrite = 1'b1;
        ALUop = 3'b010;
    end
    7'b0010011 :                 // I Type
    begin
        regWrite = 1'b1;
        ALUsrc = 1'b1;
        ALUop = 3'b010;
    end
    7'b0000011 :                 // Load type 
    begin
        regWrite = 1'b1;
        ALUsrc = 1'b1;
        memRead = 1'b1;
        memToReg = 1'b1;
    end
    7'b0100011 :                 // Store type 
    begin
        ALUsrc = 1'b1;
        memWrite = 1'b1;
        memToReg = 1'b0;         // memToReg = 1'bx
    end
    7'b1100011 :                 // Branch type
    begin
        memToReg = 1'b0;         // memToReg = 1'bx
        branch = 1'b1;
        ALUop = 3'b001;
    end
    7'b1101111 :                 // JAL Type
    begin
        regWrite = 1'b1;
        ALUsrc = 1'b0;           // ALUrsc = 1'bx
        jump = 1'b1;
        ALUop = 3'b000;          // ALUop = 3'bxxx
    end
    7'b1100111 :                 // JALR Type
    begin
        regWrite = 1'b1;
        ALUsrc = 1'b1;
        jump = 1'b1;
    end
    7'b0110111 :                 // LUI Type
    begin
        regWrite = 1'b1;
        ALUsrc = 1'b1;
        ALUop = 3'b100;
    end
    7'b0010111 :                 // AUIPC Type
    begin
        regWrite = 1'b1;
        ALUsrc = 1'b1;
    end
    7'b1110011 :                 // System Type
    begin
        ALUop = 3'b000;          // ALUop = 3'bxxx
    end
    default : ;
    endcase 
end
endmodule

immediateGenerator/immediateGenerator.v
module immediateGenerator(
    input [31:0] instr_in,
    output reg [31:0] immediate_instr
);
always @ (*)
begin
    case(instr_in[6:0])
    7'b0110011 :begin                                            // R type(not needed as R type has no immediate value,
        immediate_instr = 32'b0 ;                                        //but still kept to avoid latch)
    end
    7'b0010011, 7'b1100111, 7'b0000011, 7'b1110011 :begin        // I type (jalr, ecall, ebreak + normal I)
        immediate_instr = {{20{instr_in[31]}}, instr_in[31:20]};
    end
    7'b0100011 :begin                                            // S type
        immediate_instr = {{20{instr_in[31]}}, instr_in[31:25],instr_in[11:7]};
    end
    7'b1101111 :begin                                            // J type  
        immediate_instr = {{11{instr_in[31]}}, instr_in[31],instr_in[19:12],instr_in[20],instr_in[30:21],1'b0};
    end
    7'b1100011 :begin                                            // B type
        immediate_instr = {{19{instr_in[31]}},instr_in[31], instr_in[7], instr_in[30:25],instr_in[11:8], 1'b0};
    end
    7'b0010111, 7'b0110111 :begin                                // U type (lui + auipc)   
        immediate_instr = {instr_in[31:12], 12'b0};   
    end
    default :begin
        immediate_instr = 32'b0; 
    end             
    endcase
end
endmodule

registerFile/registerFile.v
module registerFile(
    input clk,
    input rst,         // sync reset 
    input [4:0] rs1,   // 5 bit source register 1
    input [4:0] rs2,   // 5 bit source register 2
    input [4:0] rd,    // 5 bit destination register 
    input regWrite,    // Register write enable signal
    input [31:0] writeData, // Data to be written into destination register
    output [31:0] readData1,// Data read from source register 1
    output [31:0] readData2 // Data read from source register 2
);
// 32 registers with 32 bit width 
reg [31:0] registers[0:31];

// x0 should always read as 0 (RISC-V spec)
assign readData1 = (rs1 == 0) ? 32'b0 : registers[rs1];
assign readData2 = (rs2 == 0) ? 32'b0 : registers[rs2];

integer i;
always @ (posedge clk)
begin
    if(rst)
    begin
        for(i = 0; i < 32 ; i=i+1)
        begin
            registers[i] <= 32'h0;
        end
    end
    else if(regWrite && rd!=5'd0) // Only write if regWrite is high AND destination is not x0 
    begin
        registers[rd] <= writeData ;
    end
end
always @(posedge clk) begin
    if (regWrite)
        $display("WRITE: rd=%d data=%d", rd, writeData);
end
endmodule

alu/alu_32bit.v
module alu_32bit(
    input  [31:0] op_1_in,
    input  [31:0] op_2_in,
    input  [3:0]  aluCtrl,
    output reg [31:0] result_out
);

always @(*) 
begin
    case (aluCtrl)

        4'b0000: result_out = op_1_in & op_2_in;                 // AND
        4'b0001: result_out = op_1_in | op_2_in;                 // OR
        4'b0010: result_out = op_1_in + op_2_in;                 // ADD
        4'b0011: result_out = op_1_in << op_2_in[4:0];           // SLL
        4'b0100: result_out = op_1_in ^ op_2_in;                 // XOR
        4'b0101: result_out = op_1_in >> op_2_in[4:0];           // SRL
        4'b0110: result_out = op_1_in - op_2_in;                 // SUB
        4'b0111: result_out = ($signed(op_1_in) < $signed(op_2_in)) ? 32'b1 : 32'b0; // SLT
        4'b1001: result_out = (op_1_in < op_2_in) ? 32'b1 : 32'b0; // SLTU
        4'b1101: result_out = $signed(op_1_in) >>> op_2_in[4:0]; // SRA
        4'b1000: result_out = op_2_in;                           // LUI

        default: result_out = 32'b0;

    endcase
end

endmodule

aluControl/aluControl.v
module aluControl(
    input [2:0] ALUop,       // From main Control Unit
    input [2:0] funct3,      // instruction[14:12]
    input funct7_5,          // instruction[30]
    output reg [3:0] aluCtrl // To ALU
);

    // funct3 parameters
    parameter FUNCT3_ADD  = 3'b000;
    parameter FUNCT3_SLL  = 3'b001;
    parameter FUNCT3_SLT  = 3'b010;
    parameter FUNCT3_SLTU = 3'b011;
    parameter FUNCT3_XOR  = 3'b100;
    parameter FUNCT3_SRL  = 3'b101;
    parameter FUNCT3_OR   = 3'b110;
    parameter FUNCT3_AND  = 3'b111;

    always @(*) begin
        case (ALUop)

            // Load / Store / JALR
            3'b000: aluCtrl = 4'b0010;   // ADD

            // Branch
            3'b001: aluCtrl = 4'b0110;   // SUB

            // R-type and I-type arithmetic
            3'b010: begin
                case (funct3)

                    FUNCT3_ADD: begin
                        if (funct7_5)
                            aluCtrl = 4'b0110; // SUB
                        else
                            aluCtrl = 4'b0010; // ADD
                    end

                    FUNCT3_AND: aluCtrl = 4'b0000; // AND

                    FUNCT3_OR:  aluCtrl = 4'b0001; // OR

                    FUNCT3_SLT: aluCtrl = 4'b0111; // SLT

                    FUNCT3_SLTU: aluCtrl = 4'b1001; // SLTU

                    FUNCT3_XOR: aluCtrl = 4'b0100; // XOR

                    FUNCT3_SLL: aluCtrl = 4'b0011; // SLL

                    FUNCT3_SRL: begin
                        if (funct7_5)
                            aluCtrl = 4'b1101; // SRA
                        else
                            aluCtrl = 4'b0101; // SRL
                    end

                    default: aluCtrl = 4'b1111;

                endcase
            end

            // LUI
            3'b100: aluCtrl = 4'b1000;

            default: aluCtrl = 4'b0010;

        endcase
    end

endmodule

InstructionMemory.v
module InstructionMemory (
    input [31:0] address_read,
    output [31:0] instruction_out
);

reg [31:0] Memory [0:31]; // creating memory of 32 bits width and 32 registers

assign instruction_out = Memory[address_read >> 2]; 
// PC is byte-addressed; >>2 converts byte address to word index 
integer i;

initial 
begin
    $readmemh("program.mem", Memory);
end
endmodule

PC.v
module PC(
    input [31:0] pc_in,
    input clk,
    input rst,
    output reg [31:0] pc_out
);
always @(posedge clk) 
begin
    if(rst)
        pc_out<=32'd0;
    else
        pc_out<=pc_in;
end
endmodule

top/top.v
module top(
    input clk,
    input rst
);

// PC related
wire [31:0] pc_next;
wire [31:0] pc_plus4;
wire [31:0] pc_branch;

// register file wires
wire [31:0] readData1;
wire [31:0] readData2;
wire [31:0] writeData;

// immediate
wire [31:0] imm_out;

// ALU
wire [31:0] alu_in2;
wire [31:0] alu_result;
wire [3:0] aluCtrl_wire;

// memory
wire [31:0] read_data;

// control signals
wire regWrite;
wire ALUsrc;
wire memRead;
wire memWrite;
wire memToReg;
wire branch;
wire jump;
wire [2:0] ALUop;

// branch decision
wire PCsrc;

// instruction memory connection
wire [31:0] PC_IM;
wire [31:0] instr_top;

// instantiating the PC
PC PC(
    .pc_in(pc_next),
    .clk(clk),
    .rst(rst),
    .pc_out(PC_IM)
);

// instantiating the Instruction Memory
InstructionMemory InstructionMemory(
    .address_read(PC_IM),
    .instruction_out(instr_top)
);

// instantiating the ALU control
aluControl aluControl (
    .ALUop(ALUop),
    .funct3(instr_top[14:12]),
    .funct7_5(instr_top[30]),
    .aluCtrl(aluCtrl_wire)
);

// instantiating the ALU 
alu_32bit alu_32bit (
    .op_1_in(readData1),
    .op_2_in(alu_in2),
    .aluCtrl(aluCtrl_wire),
    .result_out(alu_result)
);

// instantiating the Register File 
registerFile registerFile(
    .clk(clk),
    .rst(rst),
    .rs1(instr_top[19:15]),
    .rs2(instr_top[24:20]),
    .rd(instr_top[11:7]),
    .regWrite(regWrite),
    .writeData(writeData),
    .readData1(readData1),
    .readData2(readData2)
); 

// instantiating the Immediate Generator
immediateGenerator immediateGenerator(
        .instr_in(instr_top),
        .immediate_instr(imm_out)
    );

// instantiating the Control Unit
controlUnit controlUnit (
    .opCode(instr_top[6:0]),
    .regWrite(regWrite),
    .ALUsrc(ALUsrc),
    .memRead(memRead),
    .memWrite(memWrite),
    .memToReg(memToReg),
    .branch(branch),
    .jump(jump),
    .ALUop(ALUop)
);

// instantiaing the Data Memory
dataMemory dataMemory(
    .clk(clk),
    .rst(rst),
    .memRead(memRead),
    .memWrite(memWrite),
    .Address(alu_result),
    .write_data(readData2),
    .read_data(read_data)
);

// instantiating the adder
adder pc_adder(
    .a(PC_IM),
    .b(32'd4),
    .y(pc_plus4)
);

// ALU SRC MUX
mux2to1 alu_mux(
    .a(readData2),
    .b(imm_out),
    .sel(ALUsrc),
    .y(alu_in2)
);

// WRITE BACK MUX
mux2to1 wb_mux(
    .a(alu_result),
    .b(read_data),
    .sel(memToReg),
    .y(writeData)
);

// BRANCH ADDER
adder branch_adder(
    .a(PC_IM),
    .b(imm_out),
    .y(pc_branch)
);


assign PCsrc = branch & (alu_result == 32'b0);


//
mux2to1 pc_mux(
    .a(pc_plus4),
    .b(pc_branch),
    .sel(PCsrc),
    .y(pc_next)
);

always @(posedge clk) 
begin
    if(regWrite)
        $display("PC=%h rd=%0d data=%0d", PC_IM, instr_top[11:7], writeData);
end
endmodule

top/top_tb.v
`timescale 1ns/1ps

module top_tb;

reg clk;
reg rst;

// instantiate TOP processor
top DUT (
    .clk(clk),
    .rst(rst)
);

//  clock generation (10ns period)
always #5 clk = ~clk;

initial 
begin
    $dumpfile("top.vcd");
    $dumpvars(0, top_tb);
    //  initial values
    clk = 0;
    rst = 1;

    //  apply reset for few cycles
    #20;
    rst = 0;

    //  run processor
    #1000;

    $finish;
end



endmodule

top.vcd
$date
	Fri Mar 13 09:58:39 2026
$end
$version
	Icarus Verilog
$end
$timescale
	1ps
$end
$scope module top_tb $end
$var reg 1 ! clk $end
$var reg 1 " rst $end
$scope module DUT $end
$var wire 1 # PCsrc $end
$var wire 1 ! clk $end
$var wire 1 " rst $end
$var wire 32 $ writeData [31:0] $end
$var wire 1 % regWrite $end
$var wire 32 & read_data [31:0] $end
$var wire 32 ' readData2 [31:0] $end
$var wire 32 ( readData1 [31:0] $end
$var wire 32 ) pc_plus4 [31:0] $end
$var wire 32 * pc_next [31:0] $end
$var wire 32 + pc_branch [31:0] $end
$var wire 1 , memWrite $end
$var wire 1 - memToReg $end
$var wire 1 . memRead $end
$var wire 1 / jump $end
$var wire 32 0 instr_top [31:0] $end
$var wire 32 1 imm_out [31:0] $end
$var wire 1 2 branch $end
$var wire 32 3 alu_result [31:0] $end
$var wire 32 4 alu_in2 [31:0] $end
$var wire 4 5 aluCtrl_wire [3:0] $end
$var wire 32 6 PC_IM [31:0] $end
$var wire 1 7 ALUsrc $end
$var wire 3 8 ALUop [2:0] $end
$scope module InstructionMemory $end
$var wire 32 9 instruction_out [31:0] $end
$var wire 32 : address_read [31:0] $end
$upscope $end
$scope module PC $end
$var wire 1 ! clk $end
$var wire 1 " rst $end
$var wire 32 ; pc_in [31:0] $end
$var reg 32 < pc_out [31:0] $end
$upscope $end
$scope module aluControl $end
$var wire 3 = funct3 [2:0] $end
$var wire 1 > funct7_5 $end
$var wire 3 ? ALUop [2:0] $end
$var parameter 3 @ FUNCT3_ADD $end
$var parameter 3 A FUNCT3_AND $end
$var parameter 3 B FUNCT3_OR $end
$var parameter 3 C FUNCT3_SLL $end
$var parameter 3 D FUNCT3_SLT $end
$var parameter 3 E FUNCT3_SLTU $end
$var parameter 3 F FUNCT3_SRL $end
$var parameter 3 G FUNCT3_XOR $end
$var reg 4 H aluCtrl [3:0] $end
$upscope $end
$scope module alu_32bit $end
$var wire 4 I aluCtrl [3:0] $end
$var wire 32 J op_2_in [31:0] $end
$var wire 32 K op_1_in [31:0] $end
$var reg 32 L result_out [31:0] $end
$upscope $end
$scope module alu_mux $end
$var wire 1 7 sel $end
$var wire 32 M b [31:0] $end
$var wire 32 N a [31:0] $end
$var reg 32 O y [31:0] $end
$upscope $end
$scope module branch_adder $end
$var wire 32 P a [31:0] $end
$var wire 32 Q y [31:0] $end
$var wire 32 R b [31:0] $end
$upscope $end
$scope module controlUnit $end
$var wire 7 S opCode [6:0] $end
$var reg 3 T ALUop [2:0] $end
$var reg 1 7 ALUsrc $end
$var reg 1 2 branch $end
$var reg 1 / jump $end
$var reg 1 . memRead $end
$var reg 1 - memToReg $end
$var reg 1 , memWrite $end
$var reg 1 % regWrite $end
$upscope $end
$scope module dataMemory $end
$var wire 32 U Address [31:0] $end
$var wire 1 ! clk $end
$var wire 1 . memRead $end
$var wire 1 , memWrite $end
$var wire 32 V read_data [31:0] $end
$var wire 1 " rst $end
$var wire 32 W write_data [31:0] $end
$var integer 32 X i [31:0] $end
$upscope $end
$scope module immediateGenerator $end
$var wire 32 Y instr_in [31:0] $end
$var reg 32 Z immediate_instr [31:0] $end
$upscope $end
$scope module pc_adder $end
$var wire 32 [ a [31:0] $end
$var wire 32 \ b [31:0] $end
$var wire 32 ] y [31:0] $end
$upscope $end
$scope module pc_mux $end
$var wire 32 ^ a [31:0] $end
$var wire 32 _ b [31:0] $end
$var wire 1 # sel $end
$var reg 32 ` y [31:0] $end
$upscope $end
$scope module registerFile $end
$var wire 1 ! clk $end
$var wire 5 a rd [4:0] $end
$var wire 1 % regWrite $end
$var wire 5 b rs1 [4:0] $end
$var wire 5 c rs2 [4:0] $end
$var wire 1 " rst $end
$var wire 32 d writeData [31:0] $end
$var wire 32 e readData2 [31:0] $end
$var wire 32 f readData1 [31:0] $end
$var integer 32 g i [31:0] $end
$upscope $end
$scope module wb_mux $end
$var wire 32 h a [31:0] $end
$var wire 32 i b [31:0] $end
$var wire 1 - sel $end
$var reg 32 j y [31:0] $end
$upscope $end
$upscope $end
$upscope $end
$enddefinitions $end
$comment Show the parameter values. $end
$dumpall
b100 G
b101 F
b11 E
b10 D
b1 C
b110 B
b111 A
b0 @
$end
#0
$dumpvars
bx j
bx i
bx h
bx g
bx f
bx e
bx d
bx c
bx b
bx a
bx `
bx _
bx ^
bx ]
b100 \
bx [
bx Z
bx Y
bx X
bx W
bx V
bx U
bx T
bx S
bx R
bx Q
bx P
bx O
bx N
bx M
bx L
bx K
bx J
bx I
bx H
bx ?
x>
bx =
bx <
bx ;
bx :
bx 9
bx 8
x7
bx 6
bx 5
bx 4
bx 3
x2
bx 1
bx 0
x/
x.
x-
x,
bx +
bx *
bx )
bx (
bx '
bx &
x%
bx $
x#
1"
0!
$end
#5000
b0 &
b0 V
b0 i
0#
b101 $
b101 d
b101 j
b101 3
b101 L
b101 U
b101 h
b101 4
b101 J
b101 O
b10 8
b10 ?
b10 T
0/
02
0-
0,
0.
17
1%
b0 '
b0 N
b0 W
b0 e
b0 (
b0 K
b0 f
b10 5
b10 H
b10 I
b101 +
b101 Q
b101 _
b101 1
b101 M
b101 R
b101 Z
b10011 S
b1 a
b101 c
b0 b
0>
b0 =
b100 *
b100 ;
b100 `
b10100000000000010010011 0
b10100000000000010010011 9
b10100000000000010010011 Y
b100 )
b100 ]
b100 ^
b0 6
b0 :
b0 <
b0 P
b0 [
b100000 g
b100000 X
1!
#10000
0!
#15000
b100000 X
b100000 g
1!
#20000
0!
0"
#25000
b1010 $
b1010 d
b1010 j
b1010 3
b1010 L
b1010 U
b1010 h
b1010 4
b1010 J
b1010 O
b1010 1
b1010 M
b1010 R
b1010 Z
b10 a
b1010 c
b1000 *
b1000 ;
b1000 `
b101000000000000100010011 0
b101000000000000100010011 9
b101000000000000100010011 Y
b1110 +
b1110 Q
b1110 _
b1000 )
b1000 ]
b1000 ^
b100 6
b100 :
b100 <
b100 P
b100 [
1!
#30000
0!
#35000
b1 $
b1 d
b1 j
b1 3
b1 L
b1 U
b1 h
b1 4
b1 J
b1 O
b101 '
b101 N
b101 W
b101 e
b1 1
b1 M
b1 R
b1 Z
b101 a
b1 c
b1100 *
b1100 ;
b1100 `
b100000000001010010011 0
b100000000001010010011 9
b100000000001010010011 Y
b1001 +
b1001 Q
b1001 _
b1100 )
b1100 ]
b1100 ^
b1000 6
b1000 :
b1000 <
b1000 P
b1000 [
1!
#40000
0!
#45000
b100 $
b100 d
b100 j
b100 3
b100 L
b100 U
b100 h
b100 4
b100 J
b100 O
b0 '
b0 N
b0 W
b0 e
b100 1
b100 M
b100 R
b100 Z
b110 a
b100 c
b10000 *
b10000 ;
b10000 `
b10000000000001100010011 0
b10000000000001100010011 9
b10000000000001100010011 Y
b10000 +
b10000 Q
b10000 _
b10000 )
b10000 ]
b10000 ^
b1100 6
b1100 :
b1100 <
b1100 P
b1100 [
1!
#50000
0!
#55000
b110 $
b110 d
b110 j
b110 3
b110 L
b110 U
b110 h
b1 4
b1 J
b1 O
b101 '
b101 N
b101 W
b101 e
b101 (
b101 K
b101 f
b1 1
b1 M
b1 R
b1 Z
b1 a
b1 c
b1 b
b10100 *
b10100 ;
b10100 `
b100001000000010010011 0
b100001000000010010011 9
b100001000000010010011 Y
b10001 +
b10001 Q
b10001 _
b10100 )
b10100 ]
b10100 ^
b10000 6
b10000 :
b10000 <
b10000 P
b10000 [
1!
#60000
0!
#65000
b10 4
b10 J
b10 O
b1100 $
b1100 d
b1100 j
b10 1
b10 M
b10 R
b10 Z
b10 a
b10 c
b10 b
b1100 3
b1100 L
b1100 U
b1100 h
b11000 *
b11000 ;
b11000 `
b1000010000000100010011 0
b1000010000000100010011 9
b1000010000000100010011 Y
b1010 (
b1010 K
b1010 f
b1010 '
b1010 N
b1010 W
b1010 e
b10110 +
b10110 Q
b10110 _
b11000 )
b11000 ]
b11000 ^
b10100 6
b10100 :
b10100 <
b10100 P
b10100 [
1!
#70000
0!
#75000
b11 $
b11 d
b11 j
b11 3
b11 L
b11 U
b11 h
b11 4
b11 J
b11 O
b11 1
b11 M
b11 R
b11 Z
b101 a
b11 c
b0 b
b0 (
b0 K
b0 f
b0 '
b0 N
b0 W
b0 e
b11100 *
b11100 ;
b11100 `
b1100000000001010010011 0
b1100000000001010010011 9
b1100000000001010010011 Y
b11011 +
b11011 Q
b11011 _
b11100 )
b11100 ]
b11100 ^
b11000 6
b11000 :
b11000 <
b11000 P
b11000 [
1!
#80000
0!
#85000
b111 $
b111 d
b111 j
b111 3
b111 L
b111 U
b111 h
b111 4
b111 J
b111 O
b111 1
b111 M
b111 R
b111 Z
b110 a
b111 c
b100000 *
b100000 ;
b100000 `
b11100000000001100010011 0
b11100000000001100010011 9
b11100000000001100010011 Y
b100011 +
b100011 Q
b100011 _
b100000 )
b100000 ]
b100000 ^
b11100 6
b11100 :
b11100 <
b11100 P
b11100 [
1!
#90000
0!
#95000
b1010 $
b1010 d
b1010 j
b1010 3
b1010 L
b1010 U
b1010 h
b100 4
b100 J
b100 O
b110 (
b110 K
b110 f
b100 1
b100 M
b100 R
b100 Z
b1 a
b100 c
b1 b
b100100 *
b100100 ;
b100100 `
b10000001000000010010011 0
b10000001000000010010011 9
b10000001000000010010011 Y
b100100 +
b100100 Q
b100100 _
b100100 )
b100100 ]
b100100 ^
b100000 6
b100000 :
b100000 <
b100000 P
b100000 [
1!
#100000
0!
#105000
b101 4
b101 J
b101 O
b11 '
b11 N
b11 W
b11 e
b10001 $
b10001 d
b10001 j
b101 1
b101 M
b101 R
b101 Z
b10 a
b101 c
b10 b
b10001 3
b10001 L
b10001 U
b10001 h
b101000 *
b101000 ;
b101000 `
b10100010000000100010011 0
b10100010000000100010011 9
b10100010000000100010011 Y
b1100 (
b1100 K
b1100 f
b101001 +
b101001 Q
b101001 _
b101000 )
b101000 ]
b101000 ^
b100100 6
b100100 :
b100100 <
b100100 P
b100100 [
1!
#110000
0!
#115000
b11011 $
b11011 d
b11011 j
b10001 4
b10001 J
b10001 O
b10 8
b10 ?
b10 T
07
1%
b10001 '
b10001 N
b10001 W
b10001 e
b11011 3
b11011 L
b11011 U
b11011 h
b0 1
b0 M
b0 R
b0 Z
b110011 S
b11 a
b10 c
b1 b
b1010 (
b1010 K
b1010 f
b101100 *
b101100 ;
b101100 `
b1000001000000110110011 0
b1000001000000110110011 9
b1000001000000110110011 Y
b101000 +
b101000 Q
b101000 _
b101100 )
b101100 ]
b101100 ^
b101000 6
b101000 :
b101000 <
b101000 P
b101000 [
1!
#120000
0!
#125000
b10001 $
b10001 d
b10001 j
b1010 4
b1010 J
b1010 O
b10001 3
b10001 L
b10001 U
b10001 h
b1010 '
b1010 N
b1010 W
b1010 e
b11011 (
b11011 K
b11011 f
b110 5
b110 H
b110 I
b100 a
b1 c
b11 b
1>
b110000 *
b110000 ;
b110000 `
b1000000000100011000001000110011 0
b1000000000100011000001000110011 9
b1000000000100011000001000110011 Y
b101100 +
b101100 Q
b101100 _
b110000 )
b110000 ]
b110000 ^
b101100 6
b101100 :
b101100 <
b101100 P
b101100 [
1!
#130000
0!
#135000
b0 $
b0 d
b0 j
b10001 4
b10001 J
b10001 O
b0 3
b0 L
b0 U
b0 h
b10001 '
b10001 N
b10001 W
b10001 e
b1010 (
b1010 K
b1010 f
b0 5
b0 H
b0 I
b101 a
b10 c
b1 b
0>
b111 =
b110100 *
b110100 ;
b110100 `
b1000001111001010110011 0
b1000001111001010110011 9
b1000001111001010110011 Y
b110000 +
b110000 Q
b110000 _
b110100 )
b110100 ]
b110100 ^
b110000 6
b110000 :
b110000 <
b110000 P
b110000 [
1!
#140000
0!
#145000
b11011 $
b11011 d
b11011 j
b11011 3
b11011 L
b11011 U
b11011 h
b1 5
b1 H
b1 I
b110 a
b110 =
b111000 *
b111000 ;
b111000 `
b1000001110001100110011 0
b1000001110001100110011 9
b1000001110001100110011 Y
b110100 +
b110100 Q
b110100 _
b111000 )
b111000 ]
b111000 ^
b110100 6
b110100 :
b110100 <
b110100 P
b110100 [
1!
#150000
0!
#155000
b10 5
b10 H
b10 I
b11 a
b0 =
b111100 *
b111100 ;
b111100 `
b1000001000000110110011 0
b1000001000000110110011 9
b1000001000000110110011 Y
b111000 +
b111000 Q
b111000 _
b111100 )
b111100 ]
b111100 ^
b111000 6
b111000 :
b111000 <
b111000 P
b111000 [
1!
#160000
0!
#165000
b10001 $
b10001 d
b10001 j
b1010 4
b1010 J
b1010 O
b10001 3
b10001 L
b10001 U
b10001 h
b1010 '
b1010 N
b1010 W
b1010 e
b11011 (
b11011 K
b11011 f
b110 5
b110 H
b110 I
b100 a
b1 c
b11 b
1>
b1000000 *
b1000000 ;
b1000000 `
b1000000000100011000001000110011 0
b1000000000100011000001000110011 9
b1000000000100011000001000110011 Y
b111100 +
b111100 Q
b111100 _
b1000000 )
b1000000 ]
b1000000 ^
b111100 6
b111100 :
b111100 <
b111100 P
b111100 [
1!
#170000
0!
#175000
b0 $
b0 d
b0 j
b10001 4
b10001 J
b10001 O
b0 3
b0 L
b0 U
b0 h
b10001 '
b10001 N
b10001 W
b10001 e
b1010 (
b1010 K
b1010 f
b0 5
b0 H
b0 I
b101 a
b10 c
b1 b
0>
b111 =
b1000100 *
b1000100 ;
b1000100 `
b1000001111001010110011 0
b1000001111001010110011 9
b1000001111001010110011 Y
b1000000 +
b1000000 Q
b1000000 _
b1000100 )
b1000100 ]
b1000100 ^
b1000000 6
b1000000 :
b1000000 <
b1000000 P
b1000000 [
1!
#180000
0!
#185000
b11011 $
b11011 d
b11011 j
b11011 3
b11011 L
b11011 U
b11011 h
b1 5
b1 H
b1 I
b110 a
b110 =
b1001000 *
b1001000 ;
b1001000 `
b1000001110001100110011 0
b1000001110001100110011 9
b1000001110001100110011 Y
b1000100 +
b1000100 Q
b1000100 _
b1001000 )
b1001000 ]
b1001000 ^
b1000100 6
b1000100 :
b1000100 <
b1000100 P
b1000100 [
1!
#190000
0!
#195000
b10 5
b10 H
b10 I
b11 a
b0 =
b1001100 *
b1001100 ;
b1001100 `
b1000001000000110110011 0
b1000001000000110110011 9
b1000001000000110110011 Y
b1001000 +
b1001000 Q
b1001000 _
b1001100 )
b1001100 ]
b1001100 ^
b1001000 6
b1001000 :
b1001000 <
b1001000 P
b1001000 [
1!
#200000
0!
#205000
b10001 $
b10001 d
b10001 j
b1010 4
b1010 J
b1010 O
b10001 3
b10001 L
b10001 U
b10001 h
b1010 '
b1010 N
b1010 W
b1010 e
b11011 (
b11011 K
b11011 f
b110 5
b110 H
b110 I
b100 a
b1 c
b11 b
1>
b1010000 *
b1010000 ;
b1010000 `
b1000000000100011000001000110011 0
b1000000000100011000001000110011 9
b1000000000100011000001000110011 Y
b1001100 +
b1001100 Q
b1001100 _
b1010000 )
b1010000 ]
b1010000 ^
b1001100 6
b1001100 :
b1001100 <
b1001100 P
b1001100 [
1!
#210000
0!
#215000
b0 $
b0 d
b0 j
b10001 4
b10001 J
b10001 O
b0 3
b0 L
b0 U
b0 h
b10001 '
b10001 N
b10001 W
b10001 e
b1010 (
b1010 K
b1010 f
b0 5
b0 H
b0 I
b101 a
b10 c
b1 b
0>
b111 =
b1010100 *
b1010100 ;
b1010100 `
b1000001111001010110011 0
b1000001111001010110011 9
b1000001111001010110011 Y
b1010000 +
b1010000 Q
b1010000 _
b1010100 )
b1010100 ]
b1010100 ^
b1010000 6
b1010000 :
b1010000 <
b1010000 P
b1010000 [
1!
#220000
0!
#225000
b11011 $
b11011 d
b11011 j
b11011 3
b11011 L
b11011 U
b11011 h
b1 5
b1 H
b1 I
b110 a
b110 =
b1011000 *
b1011000 ;
b1011000 `
b1000001110001100110011 0
b1000001110001100110011 9
b1000001110001100110011 Y
b1010100 +
b1010100 Q
b1010100 _
b1011000 )
b1011000 ]
b1011000 ^
b1010100 6
b1010100 :
b1010100 <
b1010100 P
b1010100 [
1!
#230000
0!
#235000
b0 $
b0 d
b0 j
b0 4
b0 J
b0 O
b0 3
b0 L
b0 U
b0 h
1,
17
b0 8
b0 ?
b0 T
0%
b11011 '
b11011 N
b11011 W
b11011 e
b0 (
b0 K
b0 f
b10 5
b10 H
b10 I
b100011 S
b0 a
b110 c
b101 b
b10 =
b1011100 *
b1011100 ;
b1011100 `
b11000101010000000100011 0
b11000101010000000100011 9
b11000101010000000100011 Y
b1011000 +
b1011000 Q
b1011000 _
b1011100 )
b1011100 ]
b1011100 ^
b1011000 6
b1011000 :
b1011000 <
b1011000 P
b1011000 [
1!
#240000
0!
#245000
b100 $
b100 d
b100 j
b100 3
b100 L
b100 U
b100 h
b100 4
b100 J
b100 O
b100 1
b100 M
b100 R
b100 Z
b100 a
b1100000 *
b1100000 ;
b1100000 `
b11000101010001000100011 0
b11000101010001000100011 9
b11000101010001000100011 Y
b1100000 +
b1100000 Q
b1100000 _
b1100000 )
b1100000 ]
b1100000 ^
b1011100 6
b1011100 :
b1011100 <
b1011100 P
b1011100 [
b0 &
b0 V
b0 i
1!
#250000
0!
#255000
b0 3
b0 L
b0 U
b0 h
b11011 $
b11011 d
b11011 j
b0 4
b0 J
b0 O
1-
1.
1%
0,
17
b0 '
b0 N
b0 W
b0 e
b0 1
b0 M
b0 R
b0 Z
b11 S
b111 a
b0 c
b1100100 *
b1100100 ;
b1100100 `
b101010001110000011 0
b101010001110000011 9
b101010001110000011 Y
b11011 &
b11011 V
b11011 i
b1100000 +
b1100000 Q
b1100000 _
b1100100 )
b1100100 ]
b1100100 ^
b1100000 6
b1100000 :
b1100000 <
b1100000 P
b1100000 [
1!
#260000
0!
#265000
b100 3
b100 L
b100 U
b100 h
b100 4
b100 J
b100 O
b10001 '
b10001 N
b10001 W
b10001 e
b100 1
b100 M
b100 R
b100 Z
b100 c
b1101000 *
b1101000 ;
b1101000 `
b10000101010001110000011 0
b10000101010001110000011 9
b10000101010001110000011 Y
b1101000 +
b1101000 Q
b1101000 _
b1101000 )
b1101000 ]
b1101000 ^
b1100100 6
b1100100 :
b1100100 <
b1100100 P
b1100100 [
1!
#270000
0!
